xontrib/prompt_bar.py
xontrib_prompt_bar-0.5.8.dist-info/LICENSE
xontrib_prompt_bar-0.5.8.dist-info/METADATA
xontrib_prompt_bar-0.5.8.dist-info/WHEEL
xontrib_prompt_bar-0.5.8.dist-info/top_level.txt
xontrib_prompt_bar-0.5.8.dist-info/RECORD
